{   
    "speakers": {
        "npc": {
          "name": "     ",
          "face": {
            "type": "artificial",
            "modelType": "npc",
            "identifier": "cobblemon:schoolboy",
            "isLeftSide": true
          }
        }
      },
    "pages": [
        {
            "id": "greeting",
            "speaker": "npc",
            "lines": [
                "Estoy dando un paseo relajante en mi nueva bicicleta con mi novia."
            ],
            "input": {
                "type": "option",
                "vertical": false,
                "options": [
                    {
                        "text": "Close",
                        "value": "close",
                        "action": [
                            "q.dialogue.close();"
                            ]
                    }
                ]
            }
        }
        ]
    }